{
    "Topic": "1secretSpassage", 
    "Record Header": {
        "Signature": "INFO", 
        "Record Flags": {}, 
        "FormID": "01003A3A"
    }, 
    "DATA - ": {
        "Type": 0, 
        "Next Speaker": 0, 
        "Flags": {}
    }, 
    "QSTI - Quest": "fbmwMSCrimsonPlague", 
    "PNAM - Previous INFO": "01003A39", 
    "Responses": [
        {
            "TRDT - Response Data": {
                "Emotion Type": 0, 
                "Emotion Value": 50, 
                "Unused": "20 30 66", 
                "Response number": 1
            }, 
            "NAM1 - Response Text": "Outlander has found the passage, yes? Then outlander should not be here talking to Shunari. Outlander should be finding Gedna Relvel.", 
            "NAM2 - Actor notes": ""
        }
    ], 
    "Conditions": [
        {
            "Type": 0, 
            "Unused": 0, 
            "Comparison Value": 139.999999646534, 
            "Function": 58, 
            "Parameter #1": "fbmwMSCrimsonPlague", 
            "Parameter #2": "00 00 00 00"
        }, 
        {
            "Type": 0, 
            "Unused": 0, 
            "Comparison Value": 0.999999997475243, 
            "Function": 72, 
            "Parameter #1": "0ShunariSEyeTFly", 
            "Parameter #2": "00 00 00 00"
        }, 
        {
            "Type": 0, 
            "Unused": 0, 
            "Comparison Value": 0.999999997475243, 
            "Function": 71, 
            "Parameter #1": "0factMorrowind", 
            "Parameter #2": "00 00 00 00"
        }
    ], 
    "Result Script": {
        "SCHR - Basic Script Data": {
            "Unused": "00 00 00 00", 
            "RefCount": 0, 
            "CompiledSize": 0, 
            "VariableCount": 0, 
            "Type": 0
        }
    }
}