{
    "Record Header": {
        "Signature": "FLOR", 
        "Record Flags": {}, 
        "FormID": "011E019C"
    }, 
    "EDID - Editor ID": "0containUtramaUshrubU01", 
    "FULL - Name": "Trama Shrub", 
    "Model": {
        "MODL - Model Filename": "Morroblivion\\Flora\\Trama\\TramaShrub01anim.nif", 
        "MODB - Bound Radius": 501.531493733755
    }, 
    "SCRI - Script": "mwHarvestableFloraScript", 
    "PFIG - Ingredient": "0ingredUtramaUrootU01", 
    "PFPC - Seasonal ingredient production": {
        "Spring": 80, 
        "Summer ": 80, 
        "Fall": 80, 
        "Winter": 80
    }
}