{
    "Topic": "1DagonSFel", 
    "Record Header": {
        "Signature": "INFO", 
        "Record Flags": {}, 
        "FormID": "0132259B"
    }, 
    "DATA - ": {
        "Type": 0, 
        "Next Speaker": 0, 
        "Flags": {}
    }, 
    "QSTI - Quest": "MorroDefaultQuest", 
    "PNAM - Previous INFO": "0132259A", 
    "Add topics": [
        "1DagonSFel", 
        "1SorkvildStheSRaven"
    ], 
    "Responses": [
        {
            "TRDT - Response Data": {
                "Emotion Type": 0, 
                "Emotion Value": 50, 
                "Unused": "CD CD CD", 
                "Response number": 1
            }, 
            "NAM1 - Response Text": "All Dagon Fel wants to be is a simple fishing village. But recent activities of Sorkvild the Raven are a cause for concern.", 
            "NAM2 - Actor notes": ""
        }
    ], 
    "Conditions": [
        {
            "Type": 0, 
            "Unused": 0, 
            "Comparison Value": 0.999999997475243, 
            "Function": 67, 
            "Parameter #1": "DagonSFel", 
            "Parameter #2": "00 00 00 00"
        }, 
        {
            "Type": 96, 
            "Unused": 0, 
            "Comparison Value": 49.9999998737621, 
            "Function": 76, 
            "Parameter #1": 20, 
            "Parameter #2": "00 00 00 00"
        }, 
        {
            "Type": 128, 
            "Unused": 0, 
            "Comparison Value": 49.9999998737621, 
            "Function": 77, 
            "Parameter #1": "00 00 00 00", 
            "Parameter #2": "00 00 00 00"
        }, 
        {
            "Type": 0, 
            "Unused": 0, 
            "Comparison Value": 0.999999997475243, 
            "Function": 71, 
            "Parameter #1": "0factMorrowind", 
            "Parameter #2": "00 00 00 00"
        }
    ], 
    "Result Script": {
        "SCHR - Basic Script Data": {
            "Unused": "00 00 00 00", 
            "RefCount": 0, 
            "CompiledSize": 0, 
            "VariableCount": 0, 
            "Type": 0
        }
    }
}