{
    "Record Header": {
        "Signature": "CREA", 
        "Record Flags": {}, 
        "FormID": "01003B0B"
    }, 
    "EDID - Editor ID": "0CliffRacerDiseased", 
    "FULL - Name": "Diseased Cliff Racer", 
    "Model": {
        "MODL - Model Filename": "Creatures\\Cliffracer\\skeleton.nif", 
        "MODB - Bound Radius": 299.414551244051
    }, 
    "Items": [
        {
            "Item": "0ingredUracerUplumesU01", 
            "Count": 1
        }
    ], 
    "Spells": [
        "0helljoint"
    ], 
    "NIFZ - Models": [
        "body.nif", 
        ""
    ], 
    "NIFT - Texture Files Hashes": "00 00 00 00", 
    "ACBS - Configuration": {
        "Flags": {
            "Respawn": true, 
            "Flies": true, 
            "No Low Level Processing": true
        }, 
        "Base spell points": 20, 
        "Fatigue": 400, 
        "Barter gold": 0, 
        "Level (offset)": 4, 
        "Calc min": 1, 
        "Calc max": 0
    }, 
    "Factions": [
        {
            "Faction": "CreatureFaction", 
            "Rank": 0, 
            "Unused": "49 46 5A"
        }, 
        {
            "Faction": "DremoraFaction", 
            "Rank": 0, 
            "Unused": "49 46 5A"
        }, 
        {
            "Faction": "DaedraFaction", 
            "Rank": 0, 
            "Unused": "49 46 5A"
        }, 
        {
            "Faction": "0factMorrowind", 
            "Rank": 0, 
            "Unused": "00 00 00"
        }
    ], 
    "AIDT - AI Data": {
        "Aggression": 75, 
        "Confidence": 70, 
        "Energy Level": 75, 
        "Responsibility": 0, 
        "Buys/Sells and Services": {}, 
        "Teaches": "Armorer", 
        "Maximum training level": 0, 
        "Unused": "00 00"
    }, 
    "AI Packages": [
        "aaaCreatureExterior1500"
    ], 
    "DATA - Creature Data": {
        "Type": 0, 
        "Combat Skill": 65, 
        "Magic Skill": 90, 
        "Stealth Skill": 20, 
        "Soul": 3, 
        "Unused": "00 00", 
        "Health": 45, 
        "Attack Damage": 18, 
        "Strength": 50, 
        "Intelligence": 19, 
        "Willpower": 30, 
        "Agility": 50, 
        "Speed": 100, 
        "Endurance": 50, 
        "Personality": 50, 
        "Luck": 50
    }, 
    "RNAM - Attack reach": 50, 
    "TNAM - Turning Speed": 0, 
    "BNAM - Base Scale": 0.999999997475243, 
    "WNAM - Foot Weight": 2.99999999242573, 
    "CSCR - Inherits Sounds from": "0CliffRacer"
}