{
    "Record Header": {
        "Signature": "DIAL", 
        "Record Flags": {}, 
        "FormID": "01311099"
    }, 
    "EDID - Editor ID": "1plot", 
    "Quests": [
        "fbmwTRAssassins", 
        "MorroDefaultQuest"
    ], 
    "FULL - Name": "Plot", 
    "DATA - Type": 0, 
    "Child Group": [
        {
            "Topic": "1plot", 
            "Record Header": {
                "Signature": "INFO", 
                "Record Flags": {}, 
                "FormID": "0100D0B9"
            }, 
            "DATA - ": {
                "Type": 0, 
                "Next Speaker": 0, 
                "Flags": {}
            }, 
            "QSTI - Quest": "fbmwTRAssassins", 
            "PNAM - Previous INFO": "01322E41", 
            "Responses": [
                {
                    "TRDT - Response Data": {
                        "Emotion Type": 0, 
                        "Emotion Value": 50, 
                        "Unused": "CD CD CD", 
                        "Response number": 1
                    }, 
                    "NAM1 - Response Text": "Find out what you can.", 
                    "NAM2 - Actor notes": ""
                }
            ], 
            "Conditions": [
                {
                    "Type": 0, 
                    "Unused": 0, 
                    "Comparison Value": 0.999999997475243, 
                    "Function": 79, 
                    "Parameter #1": "fbmwTRAssassins", 
                    "Parameter #2": 1
                }, 
                {
                    "Type": 0, 
                    "Unused": 0, 
                    "Comparison Value": 0.999999997475243, 
                    "Function": 72, 
                    "Parameter #1": "0KingSHlaaluSHelseth", 
                    "Parameter #2": "00 00 00 00"
                }, 
                {
                    "Type": 0, 
                    "Unused": 0, 
                    "Comparison Value": 0.999999997475243, 
                    "Function": 71, 
                    "Parameter #1": "0factMorrowind", 
                    "Parameter #2": "00 00 00 00"
                }
            ], 
            "Result Script": {
                "SCHR - Basic Script Data": {
                    "Unused": "00 00 00 00", 
                    "RefCount": 0, 
                    "CompiledSize": 0, 
                    "VariableCount": 0, 
                    "Type": 0
                }
            }
        }, 
        {
            "Topic": "1plot", 
            "Record Header": {
                "Signature": "INFO", 
                "Record Flags": {}, 
                "FormID": "0100D0BA"
            }, 
            "DATA - ": {
                "Type": 0, 
                "Next Speaker": 0, 
                "Flags": {}
            }, 
            "QSTI - Quest": "fbmwTRAssassins", 
            "PNAM - Previous INFO": "0100D0B9", 
            "Responses": [
                {
                    "TRDT - Response Data": {
                        "Emotion Type": 0, 
                        "Emotion Value": 50, 
                        "Unused": "CD CD CD", 
                        "Response number": 1
                    }, 
                    "NAM1 - Response Text": "Some of my informants have learned of a possible assassination plot against our royal person. I would like more information on this.", 
                    "NAM2 - Actor notes": ""
                }, 
                {
                    "TRDT - Response Data": {
                        "Emotion Type": 0, 
                        "Emotion Value": 50, 
                        "Unused": "20 30 66", 
                        "Response number": 2
                    }, 
                    "NAM1 - Response Text": "However, I do not want to compromise the safety of my guards or of my informant. I believe, however, you would be suitable for this matter.", 
                    "NAM2 - Actor notes": ""
                }
            ], 
            "Conditions": [
                {
                    "Type": 0, 
                    "Unused": 0, 
                    "Comparison Value": 0, 
                    "Function": 79, 
                    "Parameter #1": "fbmwTRAssassins", 
                    "Parameter #2": 1
                }, 
                {
                    "Type": 128, 
                    "Unused": 0, 
                    "Comparison Value": 9.99999997475243, 
                    "Function": 58, 
                    "Parameter #1": "fbmwTRAssassins", 
                    "Parameter #2": "00 00 00 00"
                }, 
                {
                    "Type": 0, 
                    "Unused": 0, 
                    "Comparison Value": 0.999999997475243, 
                    "Function": 72, 
                    "Parameter #1": "0KingSHlaaluSHelseth", 
                    "Parameter #2": "00 00 00 00"
                }, 
                {
                    "Type": 0, 
                    "Unused": 0, 
                    "Comparison Value": 0.999999997475243, 
                    "Function": 71, 
                    "Parameter #1": "0factMorrowind", 
                    "Parameter #2": "00 00 00 00"
                }
            ], 
            "Result Script": {
                "SCHR - Basic Script Data": {
                    "Unused": "00 00 00 00", 
                    "RefCount": 1, 
                    "CompiledSize": 9, 
                    "VariableCount": 0, 
                    "Type": 0
                }, 
                "SCDA - Compiled result script": "58 10 05 00 01 00 72 01 00", 
                "SCTX - Result script source": "addtopic 1thisSmatter", 
                "References": [
                    "1thisSmatter"
                ]
            }
        }, 
        {
            "Topic": "1plot", 
            "Record Header": {
                "Signature": "INFO", 
                "Record Flags": {}, 
                "FormID": "0100D0BB"
            }, 
            "DATA - ": {
                "Type": 0, 
                "Next Speaker": 0, 
                "Flags": {}
            }, 
            "QSTI - Quest": "fbmwTRAssassins", 
            "PNAM - Previous INFO": "0100D0BA", 
            "Responses": [
                {
                    "TRDT - Response Data": {
                        "Emotion Type": 0, 
                        "Emotion Value": 50, 
                        "Unused": "69 74 69", 
                        "Response number": 1
                    }, 
                    "NAM1 - Response Text": "It seems that's been taken care of. Good work.", 
                    "NAM2 - Actor notes": ""
                }
            ], 
            "Conditions": [
                {
                    "Type": 96, 
                    "Unused": 0, 
                    "Comparison Value": 89.9999997727718, 
                    "Function": 58, 
                    "Parameter #1": "fbmwTRAssassins", 
                    "Parameter #2": "00 00 00 00"
                }, 
                {
                    "Type": 0, 
                    "Unused": 0, 
                    "Comparison Value": 0.999999997475243, 
                    "Function": 72, 
                    "Parameter #1": "0barenziah", 
                    "Parameter #2": "00 00 00 00"
                }, 
                {
                    "Type": 0, 
                    "Unused": 0, 
                    "Comparison Value": 0.999999997475243, 
                    "Function": 71, 
                    "Parameter #1": "0factMorrowind", 
                    "Parameter #2": "00 00 00 00"
                }
            ], 
            "Result Script": {
                "SCHR - Basic Script Data": {
                    "Unused": "00 00 00 00", 
                    "RefCount": 0, 
                    "CompiledSize": 0, 
                    "VariableCount": 0, 
                    "Type": 0
                }
            }
        }, 
        {
            "Topic": "1plot", 
            "Record Header": {
                "Signature": "INFO", 
                "Record Flags": {}, 
                "FormID": "0100D0BC"
            }, 
            "DATA - ": {
                "Type": 0, 
                "Next Speaker": 0, 
                "Flags": {}
            }, 
            "QSTI - Quest": "fbmwTRAssassins", 
            "PNAM - Previous INFO": "0100D0BB", 
            "Responses": [
                {
                    "TRDT - Response Data": {
                        "Emotion Type": 0, 
                        "Emotion Value": 50, 
                        "Unused": "69 74 69", 
                        "Response number": 1
                    }, 
                    "NAM1 - Response Text": "Do what you must, my friend. I am not concerned.", 
                    "NAM2 - Actor notes": ""
                }
            ], 
            "Conditions": [
                {
                    "Type": 96, 
                    "Unused": 0, 
                    "Comparison Value": 79.9999997980194, 
                    "Function": 58, 
                    "Parameter #1": "fbmwTRAssassins", 
                    "Parameter #2": "00 00 00 00"
                }, 
                {
                    "Type": 128, 
                    "Unused": 0, 
                    "Comparison Value": 89.9999997727718, 
                    "Function": 58, 
                    "Parameter #1": "fbmwTRAssassins", 
                    "Parameter #2": "00 00 00 00"
                }, 
                {
                    "Type": 0, 
                    "Unused": 0, 
                    "Comparison Value": 0.999999997475243, 
                    "Function": 72, 
                    "Parameter #1": "0barenziah", 
                    "Parameter #2": "00 00 00 00"
                }, 
                {
                    "Type": 0, 
                    "Unused": 0, 
                    "Comparison Value": 0.999999997475243, 
                    "Function": 71, 
                    "Parameter #1": "0factMorrowind", 
                    "Parameter #2": "00 00 00 00"
                }
            ], 
            "Result Script": {
                "SCHR - Basic Script Data": {
                    "Unused": "00 00 00 00", 
                    "RefCount": 0, 
                    "CompiledSize": 0, 
                    "VariableCount": 0, 
                    "Type": 0
                }
            }
        }, 
        {
            "Topic": "1plot", 
            "Record Header": {
                "Signature": "INFO", 
                "Record Flags": {}, 
                "FormID": "01322E41"
            }, 
            "DATA - ": {
                "Type": 0, 
                "Next Speaker": 0, 
                "Flags": {}
            }, 
            "QSTI - Quest": "fbmwTRAssassins", 
            "PNAM - Previous INFO": "01322E42", 
            "Responses": [
                {
                    "TRDT - Response Data": {
                        "Emotion Type": 0, 
                        "Emotion Value": 50, 
                        "Unused": "CD CD CD", 
                        "Response number": 1
                    }, 
                    "NAM1 - Response Text": "Yes...I expected you would find out as much. Other sources of mine indicate the same thing, and that the attempt will be made tomorrow night.", 
                    "NAM2 - Actor notes": ""
                }, 
                {
                    "TRDT - Response Data": {
                        "Emotion Type": 0, 
                        "Emotion Value": 50, 
                        "Unused": "CD CD CD", 
                        "Response number": 2
                    }, 
                    "NAM1 - Response Text": "Our mother must be protected at all costs, but I do not wish to tip my hand to these assassins. Here is how we will protect Barenziah.", 
                    "NAM2 - Actor notes": ""
                }
            ], 
            "Conditions": [
                {
                    "Type": 0, 
                    "Unused": 0, 
                    "Comparison Value": 1.99999999495049, 
                    "Function": 79, 
                    "Parameter #1": "fbmwTRAssassins", 
                    "Parameter #2": 1
                }, 
                {
                    "Type": 0, 
                    "Unused": 0, 
                    "Comparison Value": 0.999999997475243, 
                    "Function": 72, 
                    "Parameter #1": "0KingSHlaaluSHelseth", 
                    "Parameter #2": "00 00 00 00"
                }, 
                {
                    "Type": 0, 
                    "Unused": 0, 
                    "Comparison Value": 0.999999997475243, 
                    "Function": 71, 
                    "Parameter #1": "0factMorrowind", 
                    "Parameter #2": "00 00 00 00"
                }
            ], 
            "Result Script": {
                "SCHR - Basic Script Data": {
                    "Unused": "00 00 00 00", 
                    "RefCount": 1, 
                    "CompiledSize": 9, 
                    "VariableCount": 0, 
                    "Type": 0
                }, 
                "SCDA - Compiled result script": "58 10 05 00 01 00 72 01 00", 
                "SCTX - Result script source": "addtopic 1protectSBarenziah", 
                "References": [
                    "1protectSBarenziah"
                ]
            }
        }, 
        {
            "Topic": "1plot", 
            "Record Header": {
                "Signature": "INFO", 
                "Record Flags": {}, 
                "FormID": "01322E42"
            }, 
            "DATA - ": {
                "Type": 0, 
                "Next Speaker": 0, 
                "Flags": {}
            }, 
            "QSTI - Quest": "fbmwTRAssassins", 
            "PNAM - Previous INFO": 0, 
            "Responses": [
                {
                    "TRDT - Response Data": {
                        "Emotion Type": 0, 
                        "Emotion Value": 50, 
                        "Unused": "CD CD CD", 
                        "Response number": 1
                    }, 
                    "NAM1 - Response Text": "It must be stopped.", 
                    "NAM2 - Actor notes": ""
                }
            ], 
            "Conditions": [
                {
                    "Type": 96, 
                    "Unused": 0, 
                    "Comparison Value": 79.9999997980194, 
                    "Function": 58, 
                    "Parameter #1": "fbmwTRAssassins", 
                    "Parameter #2": "00 00 00 00"
                }, 
                {
                    "Type": 0, 
                    "Unused": 0, 
                    "Comparison Value": 1.99999999495049, 
                    "Function": 79, 
                    "Parameter #1": "fbmwTRAssassins", 
                    "Parameter #2": 1
                }, 
                {
                    "Type": 0, 
                    "Unused": 0, 
                    "Comparison Value": 0.999999997475243, 
                    "Function": 72, 
                    "Parameter #1": "0KingSHlaaluSHelseth", 
                    "Parameter #2": "00 00 00 00"
                }, 
                {
                    "Type": 0, 
                    "Unused": 0, 
                    "Comparison Value": 0.999999997475243, 
                    "Function": 71, 
                    "Parameter #1": "0factMorrowind", 
                    "Parameter #2": "00 00 00 00"
                }
            ], 
            "Result Script": {
                "SCHR - Basic Script Data": {
                    "Unused": "00 00 00 00", 
                    "RefCount": 0, 
                    "CompiledSize": 0, 
                    "VariableCount": 0, 
                    "Type": 0
                }
            }
        }, 
        {
            "Topic": "1plot", 
            "Record Header": {
                "Signature": "INFO", 
                "Record Flags": {}, 
                "FormID": "01322E43"
            }, 
            "DATA - ": {
                "Type": 0, 
                "Next Speaker": 0, 
                "Flags": {}
            }, 
            "QSTI - Quest": "fbmwTRAssassins", 
            "PNAM - Previous INFO": "0100D0BC", 
            "Add topics": [
                "1killSme", 
                "1guard", 
                "1Helseth"
            ], 
            "Responses": [
                {
                    "TRDT - Response Data": {
                        "Emotion Type": 0, 
                        "Emotion Value": 50, 
                        "Unused": "CD CD CD", 
                        "Response number": 1
                    }, 
                    "NAM1 - Response Text": "Someone try to kill me? Ridiculous! Certainly I've made my share of enemies in my life, but those times are long forgotten.", 
                    "NAM2 - Actor notes": ""
                }, 
                {
                    "TRDT - Response Data": {
                        "Emotion Type": 0, 
                        "Emotion Value": 50, 
                        "Unused": "CD CD CD", 
                        "Response number": 2
                    }, 
                    "NAM1 - Response Text": "I suppose someone might think to use me to get to my son, but with the way this palace is guarded, if someone could reach me, they could just as easily reach Helseth.", 
                    "NAM2 - Actor notes": ""
                }, 
                {
                    "TRDT - Response Data": {
                        "Emotion Type": 0, 
                        "Emotion Value": 50, 
                        "Unused": "CD CD CD", 
                        "Response number": 3
                    }, 
                    "NAM1 - Response Text": "The whole idea seems ludicrous to me. But, if someone wishes to try...I've forgotten more about defending myself than most will ever learn....", 
                    "NAM2 - Actor notes": ""
                }
            ], 
            "Conditions": [
                {
                    "Type": 0, 
                    "Unused": 0, 
                    "Comparison Value": 1.99999999495049, 
                    "Function": 79, 
                    "Parameter #1": "fbmwTRAssassins", 
                    "Parameter #2": 1
                }, 
                {
                    "Type": 0, 
                    "Unused": 0, 
                    "Comparison Value": 0.999999997475243, 
                    "Function": 72, 
                    "Parameter #1": "0barenziah", 
                    "Parameter #2": "00 00 00 00"
                }, 
                {
                    "Type": 0, 
                    "Unused": 0, 
                    "Comparison Value": 0.999999997475243, 
                    "Function": 71, 
                    "Parameter #1": "0factMorrowind", 
                    "Parameter #2": "00 00 00 00"
                }
            ], 
            "Result Script": {
                "SCHR - Basic Script Data": {
                    "Unused": "00 00 00 00", 
                    "RefCount": 1, 
                    "CompiledSize": 14, 
                    "VariableCount": 0, 
                    "Type": 0
                }, 
                "SCDA - Compiled result script": "39 10 0A 00 02 00 72 01 00 6E 3C 00 00 00", 
                "SCTX - Result script source": "setstage fbmwTRassassins 60", 
                "References": [
                    "fbmwTRAssassins"
                ]
            }
        }, 
        {
            "Topic": "1plot", 
            "Record Header": {
                "Signature": "INFO", 
                "Record Flags": {}, 
                "FormID": "01322E44"
            }, 
            "DATA - ": {
                "Type": 0, 
                "Next Speaker": 0, 
                "Flags": {}
            }, 
            "QSTI - Quest": "fbmwTRAssassins", 
            "PNAM - Previous INFO": "01322E43", 
            "Add topics": [
                "1guard", 
                "1PlitiniusSMero"
            ], 
            "Responses": [
                {
                    "TRDT - Response Data": {
                        "Emotion Type": 0, 
                        "Emotion Value": 50, 
                        "Unused": "CD CD CD", 
                        "Response number": 1
                    }, 
                    "NAM1 - Response Text": "My son believes someone would try to assassinate him? It's possible, I suppose, but not likely to succeed.", 
                    "NAM2 - Actor notes": ""
                }, 
                {
                    "TRDT - Response Data": {
                        "Emotion Type": 0, 
                        "Emotion Value": 50, 
                        "Unused": "CD CD CD", 
                        "Response number": 2
                    }, 
                    "NAM1 - Response Text": "He's more well-guarded than the emperor himself. It's all a bit overdone, if you ask me. Still...someone could be up to something.", 
                    "NAM2 - Actor notes": ""
                }, 
                {
                    "TRDT - Response Data": {
                        "Emotion Type": 0, 
                        "Emotion Value": 50, 
                        "Unused": "CD CD CD", 
                        "Response number": 3
                    }, 
                    "NAM1 - Response Text": "I suggest you speak with an old friend of mine, Plitinius Mero.", 
                    "NAM2 - Actor notes": ""
                }
            ], 
            "Conditions": [
                {
                    "Type": 0, 
                    "Unused": 0, 
                    "Comparison Value": 0.999999997475243, 
                    "Function": 79, 
                    "Parameter #1": "fbmwTRAssassins", 
                    "Parameter #2": 1
                }, 
                {
                    "Type": 0, 
                    "Unused": 0, 
                    "Comparison Value": 0.999999997475243, 
                    "Function": 72, 
                    "Parameter #1": "0barenziah", 
                    "Parameter #2": "00 00 00 00"
                }, 
                {
                    "Type": 0, 
                    "Unused": 0, 
                    "Comparison Value": 0.999999997475243, 
                    "Function": 71, 
                    "Parameter #1": "0factMorrowind", 
                    "Parameter #2": "00 00 00 00"
                }
            ], 
            "Result Script": {
                "SCHR - Basic Script Data": {
                    "Unused": "00 00 00 00", 
                    "RefCount": 1, 
                    "CompiledSize": 14, 
                    "VariableCount": 0, 
                    "Type": 0
                }, 
                "SCDA - Compiled result script": "39 10 0A 00 02 00 72 01 00 6E 14 00 00 00", 
                "SCTX - Result script source": "setstage fbmwtrassassins 20", 
                "References": [
                    "fbmwTRAssassins"
                ]
            }
        }, 
        {
            "Topic": "1plot", 
            "Record Header": {
                "Signature": "INFO", 
                "Record Flags": {}, 
                "FormID": "01322E45"
            }, 
            "DATA - ": {
                "Type": 0, 
                "Next Speaker": 0, 
                "Flags": {}
            }, 
            "QSTI - Quest": "fbmwTRAssassins", 
            "PNAM - Previous INFO": "01322E44", 
            "Add topics": [
                "1mySfriend"
            ], 
            "Responses": [
                {
                    "TRDT - Response Data": {
                        "Emotion Type": 0, 
                        "Emotion Value": 50, 
                        "Unused": "CD CD CD", 
                        "Response number": 1
                    }, 
                    "NAM1 - Response Text": "It seems you've taken care of that situation. I find the whole thing very odd, my friend. You should take care.", 
                    "NAM2 - Actor notes": ""
                }
            ], 
            "Conditions": [
                {
                    "Type": 0, 
                    "Unused": 0, 
                    "Comparison Value": 2.99999999242573, 
                    "Function": 79, 
                    "Parameter #1": "fbmwTRAssassins", 
                    "Parameter #2": 1
                }, 
                {
                    "Type": 0, 
                    "Unused": 0, 
                    "Comparison Value": 0.999999997475243, 
                    "Function": 72, 
                    "Parameter #1": "0plitiniusSmero", 
                    "Parameter #2": "00 00 00 00"
                }, 
                {
                    "Type": 0, 
                    "Unused": 0, 
                    "Comparison Value": 0.999999997475243, 
                    "Function": 71, 
                    "Parameter #1": "0factMorrowind", 
                    "Parameter #2": "00 00 00 00"
                }
            ], 
            "Result Script": {
                "SCHR - Basic Script Data": {
                    "Unused": "00 00 00 00", 
                    "RefCount": 0, 
                    "CompiledSize": 0, 
                    "VariableCount": 0, 
                    "Type": 0
                }
            }
        }, 
        {
            "Topic": "1plot", 
            "Record Header": {
                "Signature": "INFO", 
                "Record Flags": {}, 
                "FormID": "01322E46"
            }, 
            "DATA - ": {
                "Type": 0, 
                "Next Speaker": 0, 
                "Flags": {}
            }, 
            "QSTI - Quest": "fbmwTRAssassins", 
            "PNAM - Previous INFO": "01322E45", 
            "Add topics": [
                "1plot", 
                "1Barenziah", 
                "1Helseth", 
                "1newSfriend"
            ], 
            "Responses": [
                {
                    "TRDT - Response Data": {
                        "Emotion Type": 0, 
                        "Emotion Value": 50, 
                        "Unused": "CD CD CD", 
                        "Response number": 1
                    }, 
                    "NAM1 - Response Text": "A plot against Barenziah? That's ridiculous! I can't think of anyone who would want to harm her. Take care with this friend.", 
                    "NAM2 - Actor notes": ""
                }, 
                {
                    "TRDT - Response Data": {
                        "Emotion Type": 0, 
                        "Emotion Value": 50, 
                        "Unused": "CD CD CD", 
                        "Response number": 2
                    }, 
                    "NAM1 - Response Text": "King Helseth is a wary one, and delights in testing the loyalty of his new friends.", 
                    "NAM2 - Actor notes": ""
                }, 
                {
                    "TRDT - Response Data": {
                        "Emotion Type": 0, 
                        "Emotion Value": 50, 
                        "Unused": "CD CD CD", 
                        "Response number": 3
                    }, 
                    "NAM1 - Response Text": "I do not believe the King would hesitate to put his own mother in danger in order to do so.", 
                    "NAM2 - Actor notes": ""
                }
            ], 
            "Conditions": [
                {
                    "Type": 0, 
                    "Unused": 0, 
                    "Comparison Value": 1.99999999495049, 
                    "Function": 79, 
                    "Parameter #1": "fbmwTRAssassins", 
                    "Parameter #2": 1
                }, 
                {
                    "Type": 0, 
                    "Unused": 0, 
                    "Comparison Value": 0.999999997475243, 
                    "Function": 72, 
                    "Parameter #1": "0plitiniusSmero", 
                    "Parameter #2": "00 00 00 00"
                }, 
                {
                    "Type": 0, 
                    "Unused": 0, 
                    "Comparison Value": 0.999999997475243, 
                    "Function": 71, 
                    "Parameter #1": "0factMorrowind", 
                    "Parameter #2": "00 00 00 00"
                }
            ], 
            "Result Script": {
                "SCHR - Basic Script Data": {
                    "Unused": "00 00 00 00", 
                    "RefCount": 1, 
                    "CompiledSize": 14, 
                    "VariableCount": 0, 
                    "Type": 0
                }, 
                "SCDA - Compiled result script": "39 10 0A 00 02 00 72 01 00 6E 46 00 00 00", 
                "SCTX - Result script source": "setstage fbmwTrassassins 70", 
                "References": [
                    "fbmwTRAssassins"
                ]
            }
        }, 
        {
            "Topic": "1plot", 
            "Record Header": {
                "Signature": "INFO", 
                "Record Flags": {}, 
                "FormID": "01322E47"
            }, 
            "DATA - ": {
                "Type": 0, 
                "Next Speaker": 0, 
                "Flags": {}
            }, 
            "QSTI - Quest": "fbmwTRAssassins", 
            "PNAM - Previous INFO": "01322E46", 
            "Add topics": [
                "1plot", 
                "1plot", 
                "1questions", 
                "1QueenSMother", 
                "1luck"
            ], 
            "Responses": [
                {
                    "TRDT - Response Data": {
                        "Emotion Type": 0, 
                        "Emotion Value": 50, 
                        "Unused": "CD CD CD", 
                        "Response number": 1
                    }, 
                    "NAM1 - Response Text": "You're not speaking of the type of plot I'm used to, are you? Heleseth has told you of a plot against his throne? Odd. He's well protected, you know.", 
                    "NAM2 - Actor notes": ""
                }, 
                {
                    "TRDT - Response Data": {
                        "Emotion Type": 0, 
                        "Emotion Value": 50, 
                        "Unused": "CD CD CD", 
                        "Response number": 2
                    }, 
                    "NAM1 - Response Text": "I would suggest meeting his informant and seeing what he has to say. If you have any further questions, please come and speak with me.", 
                    "NAM2 - Actor notes": ""
                }, 
                {
                    "TRDT - Response Data": {
                        "Emotion Type": 0, 
                        "Emotion Value": 50, 
                        "Unused": "CD CD CD", 
                        "Response number": 3
                    }, 
                    "NAM1 - Response Text": "If the Queen Mother has sent you to me, she must feel you worthy. Good luck to you.", 
                    "NAM2 - Actor notes": ""
                }
            ], 
            "Conditions": [
                {
                    "Type": 0, 
                    "Unused": 0, 
                    "Comparison Value": 0.999999997475243, 
                    "Function": 79, 
                    "Parameter #1": "fbmwTRAssassins", 
                    "Parameter #2": 1
                }, 
                {
                    "Type": 0, 
                    "Unused": 0, 
                    "Comparison Value": 0.999999997475243, 
                    "Function": 72, 
                    "Parameter #1": "0plitiniusSmero", 
                    "Parameter #2": "00 00 00 00"
                }, 
                {
                    "Type": 0, 
                    "Unused": 0, 
                    "Comparison Value": 0.999999997475243, 
                    "Function": 71, 
                    "Parameter #1": "0factMorrowind", 
                    "Parameter #2": "00 00 00 00"
                }
            ], 
            "Result Script": {
                "SCHR - Basic Script Data": {
                    "Unused": "00 00 00 00", 
                    "RefCount": 1, 
                    "CompiledSize": 14, 
                    "VariableCount": 0, 
                    "Type": 0
                }, 
                "SCDA - Compiled result script": "39 10 0A 00 02 00 72 01 00 6E 1E 00 00 00", 
                "SCTX - Result script source": "setstage fbmwtrassassins 30", 
                "References": [
                    "fbmwTRAssassins"
                ]
            }
        }
    ]
}