{
    "Record Header": {
        "Signature": "DIAL", 
        "Record Flags": {}, 
        "FormID": "01320840"
    }, 
    "EDID - Editor ID": "1CalderaSebonySmines1", 
    "Quests": [
        "fbmwHRCalderaCorrupt"
    ], 
    "FULL - Name": "Give him the record book.", 
    "DATA - Type": 0, 
    "Child Group": [
        {
            "Topic": "1CalderaSebonySmines1", 
            "Record Header": {
                "Signature": "INFO", 
                "Record Flags": {}, 
                "FormID": "0132302F"
            }, 
            "DATA - ": {
                "Type": 0, 
                "Next Speaker": 0, 
                "Flags": {}
            }, 
            "QSTI - Quest": "fbmwHRCalderaCorrupt", 
            "PNAM - Previous INFO": 0, 
            "Responses": [
                {
                    "TRDT - Response Data": {
                        "Emotion Type": 0, 
                        "Emotion Value": 50, 
                        "Unused": "CD CD CD", 
                        "Response number": 1
                    }, 
                    "NAM1 - Response Text": "Good, yes, very good. This book shows that the Hlaalu are taking more ebony than they report to the Empire.", 
                    "NAM2 - Actor notes": ""
                }, 
                {
                    "TRDT - Response Data": {
                        "Emotion Type": 0, 
                        "Emotion Value": 50, 
                        "Unused": "CD CD CD", 
                        "Response number": 2
                    }, 
                    "NAM1 - Response Text": "Now that I have this evidence, I want the Caldera mines shut down. Return there and find a way to halt the mining.", 
                    "NAM2 - Actor notes": ""
                }, 
                {
                    "TRDT - Response Data": {
                        "Emotion Type": 0, 
                        "Emotion Value": 50, 
                        "Unused": "CD CD CD", 
                        "Response number": 3
                    }, 
                    "NAM1 - Response Text": "If the Hlaalu complain to the Duke or the Empire, we can show them these books to justify our actions.", 
                    "NAM2 - Actor notes": ""
                }
            ], 
            "Conditions": [
                {
                    "Type": 0, 
                    "Unused": 0, 
                    "Comparison Value": 0.999999997475243, 
                    "Function": 72, 
                    "Parameter #1": "0garisaSllethri", 
                    "Parameter #2": "00 00 00 00"
                }
            ], 
            "Result Script": {
                "SCHR - Basic Script Data": {
                    "Unused": "00 00 00 00", 
                    "RefCount": 4, 
                    "CompiledSize": 46, 
                    "VariableCount": 0, 
                    "Type": 0
                }, 
                "SCDA - Compiled result script": "39 10 0A 00 02 00 72 02 00 6E 64 00 00 00 39 10 0A 00 02 00 72 03 00 6E 0A 00 00 00 1C 00 01 00 52 10 0A 00 02 00 72 04 00 6E 01 00 00 00", 
                "SCTX - Result script source": "SetStage fbmwHRCalderaCorrupt 100\r\nSetStage fbmwHRCalderaDisrupt 10\r\nPlayer.RemoveItem 0bkUCalderaRecordBook2 1", 
                "References": [
                    20, 
                    "fbmwHRCalderaCorrupt", 
                    "fbmwHRCalderaDisrupt", 
                    "0bkUCalderaRecordBook2"
                ]
            }
        }
    ]
}