{
    "Record Header": {
        "Signature": "LVLI", 
        "Record Flags": {}, 
        "FormID": "011A004F"
    }, 
    "EDID - Editor ID": "0lUnUapparatus", 
    "LVLD - Chance none": 0, 
    "LVLF - Flags": {
        "Calculate from all levels <= player's level": true, 
        "Calculate for each item in count": true
    }, 
    "Leveled List Entries": [
        {
            "Level": 1, 
            "Unused": "8F 1E", 
            "Reference": "AlembicApprentice", 
            "Count": 1
        }, 
        {
            "Level": 1, 
            "Unused": "8F 1E", 
            "Reference": "CalcinatorApprentice", 
            "Count": 1
        }, 
        {
            "Level": 1, 
            "Unused": "8F 1E", 
            "Reference": "MortarPestleApprentice", 
            "Count": 1
        }, 
        {
            "Level": 1, 
            "Unused": "8F 1E", 
            "Reference": "RetortApprentice", 
            "Count": 1
        }, 
        {
            "Level": 1, 
            "Unused": "8F 1E", 
            "Reference": "0apparatusUaUspipeU01", 
            "Count": 1
        }, 
        {
            "Level": 6, 
            "Unused": "8F 1E", 
            "Reference": "AlembicJourneyMan", 
            "Count": 1
        }, 
        {
            "Level": 6, 
            "Unused": "8F 1E", 
            "Reference": "CalcinatorJourneyman", 
            "Count": 1
        }, 
        {
            "Level": 6, 
            "Unused": "8F 1E", 
            "Reference": "MortarPestleJourneyman", 
            "Count": 1
        }, 
        {
            "Level": 6, 
            "Unused": "8F 1E", 
            "Reference": "RetortJourneyman", 
            "Count": 1
        }, 
        {
            "Level": 14, 
            "Unused": "8F 1E", 
            "Reference": "AlembicExpert", 
            "Count": 1
        }, 
        {
            "Level": 14, 
            "Unused": "8F 1E", 
            "Reference": "CalcinatorExpert", 
            "Count": 1
        }, 
        {
            "Level": 14, 
            "Unused": "8F 1E", 
            "Reference": "MortarPestleExpert", 
            "Count": 1
        }, 
        {
            "Level": 14, 
            "Unused": "8F 1E", 
            "Reference": "RetortExpert", 
            "Count": 1
        }, 
        {
            "Level": 20, 
            "Unused": "8F 1E", 
            "Reference": "AlembicMaster", 
            "Count": 1
        }, 
        {
            "Level": 20, 
            "Unused": "8F 1E", 
            "Reference": "CalcinatorMaster", 
            "Count": 1
        }, 
        {
            "Level": 20, 
            "Unused": "8F 1E", 
            "Reference": "MortarPestleMaster", 
            "Count": 1
        }, 
        {
            "Level": 20, 
            "Unused": "8F 1E", 
            "Reference": "RetortMaster", 
            "Count": 1
        }
    ]
}