{
    "Topic": "1DivaythSFyr", 
    "Record Header": {
        "Signature": "INFO", 
        "Record Flags": {}, 
        "FormID": "01321E01"
    }, 
    "DATA - ": {
        "Type": 0, 
        "Next Speaker": 0, 
        "Flags": {}
    }, 
    "QSTI - Quest": "MorroDefaultQuest", 
    "PNAM - Previous INFO": "01321E00", 
    "Add topics": [
        "1DivaythSFyr", 
        "1DwemerSartifacts", 
        "1Daedric", 
        "1corprusSvictims"
    ], 
    "Responses": [
        {
            "TRDT - Response Data": {
                "Emotion Type": 0, 
                "Emotion Value": 50, 
                "Unused": "CD CD CD", 
                "Response number": 1
            }, 
            "NAM1 - Response Text": "Divayth Fyr is one of the oldest mortals on Tamriel. He could be the Telvanni Archmagister, but he doesn't care about that stuff.", 
            "NAM2 - Actor notes": ""
        }, 
        {
            "TRDT - Response Data": {
                "Emotion Type": 0, 
                "Emotion Value": 50, 
                "Unused": "CD CD CD", 
                "Response number": 2
            }, 
            "NAM1 - Response Text": "He just wants to collect Dwemer artifacts and Daedric artifacts and corprus victims.", 
            "NAM2 - Actor notes": ""
        }, 
        {
            "TRDT - Response Data": {
                "Emotion Type": 0, 
                "Emotion Value": 50, 
                "Unused": "CD CD CD", 
                "Response number": 3
            }, 
            "NAM1 - Response Text": "He welcomes thieves and adventurers, says they can have anything they can get away with.", 
            "NAM2 - Actor notes": ""
        }, 
        {
            "TRDT - Response Data": {
                "Emotion Type": 0, 
                "Emotion Value": 50, 
                "Unused": "CD CD CD", 
                "Response number": 4
            }, 
            "NAM1 - Response Text": "He must have a right rich booty in there, considering the ones that go in and don't come out.", 
            "NAM2 - Actor notes": ""
        }
    ], 
    "Conditions": [
        {
            "Type": 0, 
            "Unused": 0, 
            "Comparison Value": 0.999999997475243, 
            "Function": 67, 
            "Parameter #1": "TelSFyr", 
            "Parameter #2": "00 00 00 00"
        }, 
        {
            "Type": 96, 
            "Unused": 0, 
            "Comparison Value": 29.9999999242573, 
            "Function": 76, 
            "Parameter #1": 20, 
            "Parameter #2": "00 00 00 00"
        }, 
        {
            "Type": 0, 
            "Unused": 0, 
            "Comparison Value": 0.999999997475243, 
            "Function": 71, 
            "Parameter #1": "noLore", 
            "Parameter #2": "00 00 00 00"
        }, 
        {
            "Type": 0, 
            "Unused": 0, 
            "Comparison Value": 0.999999997475243, 
            "Function": 71, 
            "Parameter #1": "0factMorrowind", 
            "Parameter #2": "00 00 00 00"
        }
    ], 
    "Result Script": {
        "SCHR - Basic Script Data": {
            "Unused": "00 00 00 00", 
            "RefCount": 0, 
            "CompiledSize": 0, 
            "VariableCount": 0, 
            "Type": 0
        }
    }
}