{
    "Record Header": {
        "Signature": "SPEL", 
        "Record Flags": {}, 
        "FormID": "01060014"
    }, 
    "EDID - Editor ID": "0burningShand", 
    "FULL - Name": "Burning Hand", 
    "SPIT - ": {
        "Type": 2, 
        "Cost": 0, 
        "Level": 0, 
        "Flags": {
            "Manual Spell Cost": true
        }, 
        "Unused": "00 00 00"
    }, 
    "Effects": [
        {
            "EFID - Magic effect name": 1195657542, 
            "EFIT - ": {
                "Magic effect name": 1195657542, 
                "Magnitude": 50, 
                "Area": 0, 
                "Duration": 1, 
                "Type": 2, 
                "Actor Value": 8
            }
        }
    ]
}